nanoserver/__init__.py
nanoserver/server.py
nanoserver-0.1.0.dist-info/licenses/LICENSE
nanoserver-0.1.0.dist-info/METADATA
nanoserver-0.1.0.dist-info/WHEEL
nanoserver-0.1.0.dist-info/top_level.txt
nanoserver-0.1.0.dist-info/RECORD
