Metadata-Version: 2.4
Name: nanoserver
Version: 0.1.0
Summary: Lightweight HTTP API server using Python stdlib
Author-email: Taufiqul Haque Khan Tusar <taufiqkhantusar@gmail.com>
License-Expression: MIT
Project-URL: Homepage, https://github.com/taufiq-ai/nanoserver
Project-URL: Issues, https://github.com/taufiq-ai/nanoserver/issues
Classifier: Programming Language :: Python :: 3
Classifier: Operating System :: OS Independent
Requires-Python: >=3.10
License-File: LICENSE
Dynamic: license-file
